arsenai/__init__.py
arsenai/util.py
arsenai/api/__init__.py
arsenai/api/fnc_generate.py
arsenai/cli/__init__.py
arsenai/cli/arsenai.py
arsenai/description/__init__.py
arsenai/description/actuator_definition.py
arsenai/description/agent_definition.py
arsenai/description/environment_definition.py
arsenai/description/parameter_definition.py
arsenai/description/phase_config_definition.py
arsenai/description/run_config_definition.py
arsenai/description/sensor_definition.py
arsenai/description/simulation_definition.py
arsenai/generator/__init__.py
arsenai/generator/analyzer.py
arsenai/generator/designer.py
arsenai/generator/experiment.py
arsenai/generator/generator.py
arsenai/schedule/__init__.py
arsenai/schedule/phase.py
arsenai/schedule/schedule.py
palaestrai_arsenai-3.5.4.1.dist-info/licenses/LICENSE
palaestrai_arsenai-3.5.4.1.dist-info/METADATA
palaestrai_arsenai-3.5.4.1.dist-info/WHEEL
palaestrai_arsenai-3.5.4.1.dist-info/entry_points.txt
palaestrai_arsenai-3.5.4.1.dist-info/top_level.txt
palaestrai_arsenai-3.5.4.1.dist-info/RECORD
