Metadata-Version: 2.4
Name: palaestrai-arsenai
Version: 3.5.4.1
Summary: Adversarial Resilience Learning Design of Experiments.
Author-email: The ARL Developers <stephan.balduin@offis.de>
Project-URL: Homepage, http://docs.palaestr.ai
Project-URL: Bug Tracker, https://gitlab.com/arl2/palaestrai-arsenai/-/issues
Classifier: Development Status :: 4 - Beta
Classifier: Intended Audience :: Science/Research
Classifier: License :: OSI Approved :: GNU Lesser General Public License v2 (LGPLv2)
Classifier: Natural Language :: English
Classifier: Operating System :: OS Independent
Classifier: Programming Language :: Python
Classifier: Programming Language :: Python :: 3
Classifier: Programming Language :: Python :: 3.6
Classifier: Programming Language :: Python :: 3.7
Classifier: Programming Language :: Python :: 3.8
Classifier: Topic :: Scientific/Engineering
Classifier: Topic :: Scientific/Engineering :: Artificial Intelligence
Requires-Python: >=3.10
License-File: LICENSE
Requires-Dist: click
Requires-Dist: numpy
Requires-Dist: pandas
Requires-Dist: doepy
Requires-Dist: ruamel.yaml
Requires-Dist: palaestrai~=3.5.0
Provides-Extra: dev
Requires-Dist: twine; extra == "dev"
Requires-Dist: setuptools; extra == "dev"
Requires-Dist: black==22.3.0; extra == "dev"
Requires-Dist: build; extra == "dev"
Dynamic: license-file
